DESIGN
GNUmakefile
MANIFEST.in
README
TODO
base32.c
base32.h
ez_setup.py
setup.py
test.c
zbase32/__init__.py
zbase32/_version.py
zbase32/zbase32.py
zbase32/zbase32id.py
zbase32.egg-info/PKG-INFO
zbase32.egg-info/SOURCES.txt
zbase32.egg-info/dependency_links.txt
zbase32.egg-info/not-zip-safe
zbase32.egg-info/requires.txt
zbase32.egg-info/top_level.txt
zbase32/test/__init__.py
zbase32/test/test_zbase32.py